README.md
setup.py
comagic/__init__.py
comagic/comagic.py
comagic/exceptions.py
comagic_wrapper.egg-info/PKG-INFO
comagic_wrapper.egg-info/SOURCES.txt
comagic_wrapper.egg-info/dependency_links.txt
comagic_wrapper.egg-info/requires.txt
comagic_wrapper.egg-info/top_level.txt