Metadata-Version: 1.2
Name: comagic-wrapper
Version: 0.0.4.2
Summary: Comagic wrapper
Home-page: https://github.com/bzdvdn/comagic-dataapi-wrapper.git
Author: bzdvdn
Author-email: bzdv.dn@gmail.com
License: MIT
Platform: UNKNOWN
Requires-Python: >=3.6
